README.rst
setup.py
pybinsim/__init__.py
pybinsim/application.py
pybinsim/convolver.py
pybinsim/filterstorage.py
pybinsim/osc_receiver.py
pybinsim/pose.py
pybinsim/soundhandler.py
pybinsim/spark_fun.py
pybinsim/utility.py
pybinsim.egg-info/PKG-INFO
pybinsim.egg-info/SOURCES.txt
pybinsim.egg-info/dependency_links.txt
pybinsim.egg-info/requires.txt
pybinsim.egg-info/top_level.txt