Metadata-Version: 1.1
Name: pybinsim
Version: 1.2.0
Summary: Real-time dynamic binaural synthesis with head tracking.
Home-page: https://github.com/pyBinSim/pyBinSim
Author: Annika Neidhardt, Florian Klein, Thomas Koellmer
Author-email: thomas.koellmer@tu-ilmenau.de
License: MIT
Platform: any
Classifier: Development Status :: 4 - Beta
Classifier: Topic :: Multimedia :: Sound/Audio
Classifier: Operating System :: MacOS :: MacOS X
Classifier: Operating System :: Microsoft :: Windows
Classifier: Operating System :: POSIX :: Linux
Classifier: Programming Language :: Python
Classifier: Programming Language :: Python :: 3
Classifier: Programming Language :: Python :: 3.4
Classifier: Programming Language :: Python :: 3.5
Classifier: Programming Language :: Python :: 3.6
Classifier: License :: OSI Approved :: MIT License
